qccodec/__init__.py
qccodec/cli.py
qccodec/codec.py
qccodec/exceptions.py
qccodec/models.py
qccodec/registry.py
qccodec/encoders/__init__.py
qccodec/encoders/crest.py
qccodec/encoders/orca.py
qccodec/encoders/terachem.py
qccodec/parsers/__init__.py
qccodec/parsers/crest.py
qccodec/parsers/orca.py
qccodec/parsers/terachem.py
qccodec/parsers/utils.py
qccodec-0.9.1.dist-info/METADATA
qccodec-0.9.1.dist-info/WHEEL
qccodec-0.9.1.dist-info/entry_points.txt
qccodec-0.9.1.dist-info/licenses/LICENSE
qccodec-0.9.1.dist-info/RECORD
