Metadata-Version: 2.4
Name: qccodec
Version: 0.9.1
Summary: A package for parsing Quantum Chemistry program file outputs into structured qcio data objects.
Project-URL: Homepage, https://github.com/coltonbh/qccodec
Project-URL: Documentation, https://github.com/coltonbh/qccodec#readme
Project-URL: Source, https://github.com/coltonbh/qccodec
Project-URL: Changelog, https://github.com/coltonbh/qccodec/blob/master/CHANGELOG.md
Project-URL: Bug Tracker, https://github.com/coltonbh/qccodec/issues
Author-email: Colton Hicks <github@coltonhicks.com>
License: The MIT License (MIT)
License-File: LICENSE
Keywords: computational chemistry,file parser,parsing,qcio,quantum chemistry,scientific computing
Classifier: Intended Audience :: Developers
Classifier: Intended Audience :: Science/Research
Classifier: License :: OSI Approved :: MIT License
Classifier: Operating System :: OS Independent
Classifier: Programming Language :: Python :: 3.10
Classifier: Programming Language :: Python :: 3.11
Classifier: Programming Language :: Python :: 3.12
Classifier: Programming Language :: Python :: 3.13
Classifier: Programming Language :: Python :: 3.14
Classifier: Topic :: Scientific/Engineering :: Chemistry
Classifier: Topic :: Scientific/Engineering :: Physics
Requires-Python: >=3.10
Requires-Dist: qcconst>=0.2.1
Requires-Dist: qcio>=0.16.0
Requires-Dist: tomli-w>=1.0.0
